golding_NEURON/__init__.py
golding_NEURON/ap_adjuster.spec
golding_NEURON/cell.py
golding_NEURON/cell_calc.py
golding_NEURON/compile_mechs.py
golding_NEURON/data.py
golding_NEURON/golding_NEURON_default_config.json
golding_NEURON/itd_job.py
golding_NEURON/itd_job_builder.py
golding_NEURON/math_calc.py
golding_NEURON/nrn_types.py
golding_NEURON/nsg_portal.py
golding_NEURON/plots.py
golding_NEURON/readme.md
golding_NEURON/sims.py
golding_NEURON/syns.py
golding_NEURON/utils.py
golding_NEURON/cells/151124_03.asc
golding_NEURON/cells/151124_10P.asc
golding_NEURON/cells/151124_11P.asc
golding_NEURON/cells/151201_02_LOOK.asc
golding_NEURON/cells/151201_05_LOOK.asc
golding_NEURON/cells/151201_06P.asc
golding_NEURON/cells/151209_03P.asc
golding_NEURON/cells/151209_06_LOOK.asc
golding_NEURON/cells/151209_09O.asc
golding_NEURON/cells/151210_02P.asc
golding_NEURON/cells/151210_03P_LOOK.asc
golding_NEURON/cells/151210_04P_LOOK.asc
golding_NEURON/cells/151210_05p.asc
golding_NEURON/cells/151210_07O_LOOK.asc
golding_NEURON/cells/151214_03.asc
golding_NEURON/cells/151214_09p.asc
golding_NEURON/cells/151214_10P.asc
golding_NEURON/cells/151217_03P_LOOK.asc
golding_NEURON/cells/151217_04P.asc
golding_NEURON/cells/151217_12p.asc
golding_NEURON/cells/160105_10.asc
golding_NEURON/cells/160105_12P.asc
golding_NEURON/cells/160105_14P.asc
golding_NEURON/cells/160105_15P.asc
golding_NEURON/cells/160106_03P_LOOK.asc
golding_NEURON/cells/160106_04_LOOK.asc
golding_NEURON/cells/160111_02P.asc
golding_NEURON/cells/160112_16P.asc
golding_NEURON/cells/160112_19P.asc
golding_NEURON/cells/160112_20P_LOOK.asc
golding_NEURON/cells/160112_26P_LOOK.asc
golding_NEURON/cells/160112_27P.asc
golding_NEURON/cells/160123_08_LOOK.asc
golding_NEURON/cells/160126_08_LOOK.asc
golding_NEURON/cells/160305_01p.asc
golding_NEURON/cells/160305_09P.asc
golding_NEURON/cells/160317_16_LOOK.asc
golding_NEURON/cells/160317_20P.asc
golding_NEURON/cells/160318_16.asc
golding_NEURON/cells/160318_21p.asc
golding_neuron-0.1.13.dist-info/METADATA
golding_neuron-0.1.13.dist-info/WHEEL
golding_neuron-0.1.13.dist-info/entry_points.txt
golding_neuron-0.1.13.dist-info/licenses/LICENSE
golding_neuron-0.1.13.dist-info/RECORD
