Metadata-Version: 2.4
Name: golding_NEURON
Version: 0.1.13
Summary: Golding Lab NEURON project library
Project-URL: Project, https://www.github.com/jaredcasarez/golding_NEURON
Project-URL: Lab, https://goldinglab.org
Author-email: Jared Casarez <jaredcasarez1@gmail.com>
License-File: LICENSE
Requires-Python: >=3.8
Requires-Dist: matplotlib>=3.4
Requires-Dist: neuron>=8.0
Requires-Dist: numpy>=1.21
Requires-Dist: pandas>=1.3
Requires-Dist: platformdirs>=2.4
Requires-Dist: pytest>=6.2
Requires-Dist: requests>=2.25
Requires-Dist: scipy>=1.7
